pytorch_mjolnir/__init__.py
pytorch_mjolnir/experiment.py
pytorch_mjolnir/remote_run.py
pytorch_mjolnir/supervised_experiment.py
pytorch_mjolnir-0.1.0.dist-info/LICENSE
pytorch_mjolnir-0.1.0.dist-info/METADATA
pytorch_mjolnir-0.1.0.dist-info/WHEEL
pytorch_mjolnir-0.1.0.dist-info/entry_points.txt
pytorch_mjolnir-0.1.0.dist-info/top_level.txt
pytorch_mjolnir-0.1.0.dist-info/RECORD
