Metadata-Version: 2.1
Name: pytorch-mjolnir
Version: 0.1.0
Summary: A catalyst for experiments with lightning.
Home-page: https://github.com/penguinmenac3/pytorch-mjolnir
Author: Michael Fuerst
Author-email: mail@michaelfuerst.de
License: MIT
Download-URL: https://github.com/penguinmenac3/pytorch-mjolnir/tarball/0.1.0
Platform: UNKNOWN
Classifier: Development Status :: 3 - Alpha
Classifier: Intended Audience :: Developers
Classifier: Programming Language :: Python
Requires-Dist: torch
Requires-Dist: torchvision
Requires-Dist: pytorch-lightning
Provides-Extra: dev
Requires-Dist: nose2 ; extra == 'dev'
Requires-Dist: packaging ; extra == 'dev'
Requires-Dist: jlabdev ; extra == 'dev'
